py_return_success_or_error/__init__.py
py_return_success_or_error/imports.py
py_return_success_or_error/py.typed
py_return_success_or_error/bases/usecase_base.py
py_return_success_or_error/core/empty.py
py_return_success_or_error/core/return_success_or_error.py
py_return_success_or_error/interfaces/app_error.py
py_return_success_or_error/interfaces/datasource.py
py_return_success_or_error/interfaces/parameters_return_result.py
py_return_success_or_error/mixins/repository_mixin.py
py_return_success_or_error/mixins/thread_mixin.py
py_return_success_or_error-0.6.1.dist-info/METADATA
py_return_success_or_error-0.6.1.dist-info/WHEEL
py_return_success_or_error-0.6.1.dist-info/licenses/LICENSE
py_return_success_or_error-0.6.1.dist-info/RECORD
