Metadata-Version: 2.4
Name: py-return-success-or-error
Version: 0.6.1
Summary: A biblioteca `py-return-success-or-error` é uma solução robusta para tratamento de retornos e erros em aplicações Python, seguindo princípios de design limpo e arquitetura limpa.
Project-URL: Documentation, https://py-return-success-or-error.readthedocs.io/pt-br/latest/
Project-URL: Repository, https://github.com/pwlimaverde/py-return-success-or-error
Project-URL: Issues, https://github.com/pwlimaverde/py-return-success-or-error/issues
Author-email: pwlimaverde <pwlimaverde@gmail.com>
License-Expression: MIT
License-File: LICENSE
Classifier: Development Status :: 4 - Beta
Classifier: Intended Audience :: Developers
Classifier: License :: OSI Approved :: MIT License
Classifier: Natural Language :: Portuguese (Brazilian)
Classifier: Programming Language :: Python :: 3.13
Classifier: Topic :: Software Development :: Libraries :: Python Modules
Classifier: Topic :: Utilities
Classifier: Typing :: Typed
Requires-Python: >=3.13
